Metadata-Version: 2.1
Name: faons
Version: 0.0.3
Summary: UNKNOWN
License: UNKNOWN
Platform: UNKNOWN
